{
  "_class": "shapeGroup",
  "clippingMaskMode": 0,
  "do_objectID": "2D46600D-44C9-403C-B68F-DFC06ADDFD84",
  "exportOptions": {
    "_class": "exportOptions",
    "exportFormats": [
    ],
    "includedLayerIds": [
    ],
    "layerOptions": 0,
    "shouldTrim": false
  },
  "frame": {
    "_class": "rect",
    "constrainProportions": false,
    "height": 20,
    "width": 12,
    "x": 0,
    "y": 0
  },
  "hasClickThrough": false,
  "hasClippingMask": false,
  "isFlippedHorizontal": false,
  "isFlippedVertical": false,
  "isLocked": false,
  "isVisible": true,
  "layerListExpandedType": 0,
  "layers": [
    {
      "class": "rectangle",
      "id": "C135AD71-E67B-4243-9089-F088A6C198B0"
    }
  ],
  "name": "Rectangle 253",
  "nameIsFixed": false,
  "resizingConstraint": 63,
  "resizingType": 0,
  "rotation": 0,
  "shouldBreakMaskChain": false,
  "style": {
    "_class": "style",
    "blur": {
      "_class": "blur",
      "center": "{0.5, 0.5}",
      "do_objectID": "47EEEB74-E46A-4B57-BC43-BDC77D4DF44B",
      "isEnabled": false,
      "motionAngle": 0,
      "radius": 13.33333333333333,
      "type": 0
    },
    "borders": [
      {
        "_class": "border",
        "color": {
          "_class": "color",
          "alpha": 1,
          "blue": 0.592,
          "green": 0.592,
          "red": 0.592
        },
        "do_objectID": "4BA7540E-77FD-49F6-BFBC-369905B697FF",
        "fillType": 0,
        "isEnabled": false,
        "position": 1,
        "thickness": 1.333333333333333
      }
    ],
    "endDecorationType": 0,
    "fills": [
      {
        "_class": "fill",
        "color": {
          "_class": "color",
          "alpha": 1,
          "blue": 0.1490196078431373,
          "green": 0.1490196078431373,
          "red": 0.1490196078431373
        },
        "do_objectID": "87B68E79-A5B4-4B48-8EAD-AA8FCF66D68B",
        "fillType": 0,
        "gradient": {
          "_class": "gradient",
          "elipseLength": 1,
          "from": "{0.5, 0}",
          "gradientType": 0,
          "shouldSmoothenOpacity": true,
          "stops": [
            {
              "_class": "gradientStop",
              "color": {
                "_class": "color",
                "alpha": 1,
                "blue": 0.15,
                "green": 0.15,
                "red": 0.15
              },
              "position": 0
            },
            {
              "_class": "gradientStop",
              "color": {
                "_class": "color",
                "alpha": 1,
                "blue": 0.05,
                "green": 0.05,
                "red": 0.05
              },
              "position": 1
            }
          ],
          "to": "{0.5, 1}"
        },
        "isEnabled": true,
        "noiseIndex": 0,
        "noiseIntensity": 0,
        "patternFillType": 0,
        "patternTileScale": 1
      }
    ],
    "innerShadows": [
      {
        "_class": "innerShadow",
        "blurRadius": 0,
        "color": {
          "_class": "color",
          "alpha": 1,
          "blue": 0.3932488952020202,
          "green": 0.8505105973686136,
          "red": 1
        },
        "contextSettings": {
          "_class": "graphicsContextSettings",
          "blendMode": 0,
          "opacity": 1
        },
        "do_objectID": "17347D89-0E34-4BD5-8FA1-8373096A9BBE",
        "isEnabled": false,
        "offsetX": 0,
        "offsetY": 1,
        "spread": 0
      }
    ],
    "miterLimit": 10,
    "shadows": [
      {
        "_class": "shadow",
        "blurRadius": 0,
        "color": {
          "_class": "color",
          "alpha": 0.06,
          "blue": 0,
          "green": 0,
          "red": 0
        },
        "contextSettings": {
          "_class": "graphicsContextSettings",
          "blendMode": 1,
          "opacity": 1
        },
        "do_objectID": "638FA9AE-F316-47D5-85B6-1AF0F7693AEC",
        "isEnabled": false,
        "offsetX": 0,
        "offsetY": 0,
        "spread": 1
      }
    ],
    "startDecorationType": 0
  },
  "windingRule": 1
}