{
  "_class": "rectangle",
  "booleanOperation": 0,
  "do_objectID": "7C30892C-D49C-4EE6-ADC4-3E5483C09B9A",
  "edited": false,
  "exportOptions": {
    "_class": "exportOptions",
    "exportFormats": [
    ],
    "includedLayerIds": [
    ],
    "layerOptions": 0,
    "shouldTrim": false
  },
  "fixedRadius": 0.3333333333333333,
  "frame": {
    "_class": "rect",
    "constrainProportions": false,
    "height": 1.333333333333333,
    "width": 1.333333333333333,
    "x": 1.333333333333333,
    "y": 14.66666666666667
  },
  "hasConvertedToNewRoundCorners": true,
  "isFlippedHorizontal": false,
  "isFlippedVertical": false,
  "isLocked": false,
  "isVisible": true,
  "layerListExpandedType": 0,
  "name": "Rectangle 294",
  "nameIsFixed": false,
  "path": {
    "_class": "path",
    "isClosed": true,
    "pointRadiusBehaviour": 0,
    "points": [
      {
        "_class": "curvePoint",
        "cornerRadius": 0.3333333333333333,
        "curveFrom": "{0, 0}",
        "curveMode": 1,
        "curveTo": "{0, 0}",
        "do_objectID": "D2C16E67-44F8-4E4C-B946-46BEB1E7A023",
        "hasCurveFrom": false,
        "hasCurveTo": false,
        "point": "{0, 0}"
      },
      {
        "_class": "curvePoint",
        "cornerRadius": 0.3333333333333333,
        "curveFrom": "{1, 0}",
        "curveMode": 1,
        "curveTo": "{1, 0}",
        "do_objectID": "15C49A59-8D0E-42D2-A6EE-90DC0417D29B",
        "hasCurveFrom": false,
        "hasCurveTo": false,
        "point": "{1, 0}"
      },
      {
        "_class": "curvePoint",
        "cornerRadius": 0.3333333333333333,
        "curveFrom": "{1, 1}",
        "curveMode": 1,
        "curveTo": "{1, 1}",
        "do_objectID": "38489E2B-9F7B-4AC0-AB23-079F307C5686",
        "hasCurveFrom": false,
        "hasCurveTo": false,
        "point": "{1, 1}"
      },
      {
        "_class": "curvePoint",
        "cornerRadius": 0.3333333333333333,
        "curveFrom": "{0, 1}",
        "curveMode": 1,
        "curveTo": "{0, 1}",
        "do_objectID": "C9B3BACB-DF84-4947-8E91-2149C19355E1",
        "hasCurveFrom": false,
        "hasCurveTo": false,
        "point": "{0, 1}"
      }
    ]
  },
  "resizingConstraint": 63,
  "resizingType": 0,
  "rotation": 0,
  "shouldBreakMaskChain": false
}