{
  "_class": "shapeGroup",
  "clippingMaskMode": 0,
  "do_objectID": "8524087C-68C9-4B2C-B7D5-39C90B544463",
  "exportOptions": {
    "_class": "exportOptions",
    "exportFormats": [
    ],
    "includedLayerIds": [
    ],
    "layerOptions": 0,
    "shouldTrim": false
  },
  "frame": {
    "_class": "rect",
    "constrainProportions": true,
    "height": 13.33333333333333,
    "width": 13.33333333333333,
    "x": 0,
    "y": 0
  },
  "hasClickThrough": false,
  "hasClippingMask": false,
  "isFlippedHorizontal": false,
  "isFlippedVertical": false,
  "isLocked": false,
  "isVisible": true,
  "layerListExpandedType": 0,
  "layers": [
    {
      "class": "rectangle",
      "id": "8BC8532C-71ED-4FC3-8D42-34AAC54CB49D"
    }
  ],
  "name": "Rectangle 1568",
  "nameIsFixed": false,
  "resizingConstraint": 63,
  "resizingType": 0,
  "rotation": 0,
  "shouldBreakMaskChain": false,
  "style": {
    "_class": "style",
    "blur": {
      "_class": "blur",
      "center": "{0.5, 0.5}",
      "do_objectID": "38B90A80-1C3A-418E-9F9C-B41BC22AD4AC",
      "isEnabled": false,
      "motionAngle": 0,
      "radius": 13.33333333333333,
      "type": 0
    },
    "borders": [
      {
        "_class": "border",
        "color": {
          "_class": "color",
          "alpha": 1,
          "blue": 0.592,
          "green": 0.592,
          "red": 0.592
        },
        "do_objectID": "170E3AC6-C235-4D5B-A43D-2C6E6DD75297",
        "fillType": 0,
        "isEnabled": false,
        "position": 1,
        "thickness": 1.333333333333333
      }
    ],
    "endDecorationType": 0,
    "fills": [
      {
        "_class": "fill",
        "color": {
          "_class": "color",
          "alpha": 1,
          "blue": 0.5568627450980392,
          "green": 0.247058823529412,
          "red": 0.04705882352941183
        },
        "do_objectID": "F2448964-D02C-4BE9-9969-30440B1255C9",
        "fillType": 0,
        "gradient": {
          "_class": "gradient",
          "elipseLength": 1,
          "from": "{0.5, 0}",
          "gradientType": 0,
          "shouldSmoothenOpacity": true,
          "stops": [
            {
              "_class": "gradientStop",
              "color": {
                "_class": "color",
                "alpha": 1,
                "blue": 0.5584874574829932,
                "green": 0.2473088632527391,
                "red": 0.04835861448257687
              },
              "position": 0
            },
            {
              "_class": "gradientStop",
              "color": {
                "_class": "color",
                "alpha": 1,
                "blue": 0.403921568627451,
                "green": 0.1647058823529411,
                "red": 0.01176470588235294
              },
              "position": 1
            }
          ],
          "to": "{0.5, 1}"
        },
        "isEnabled": true,
        "noiseIndex": 0,
        "noiseIntensity": 0,
        "patternFillType": 0,
        "patternTileScale": 1
      }
    ],
    "miterLimit": 10,
    "startDecorationType": 0
  },
  "windingRule": 1
}