{
  "_class": "shapeGroup",
  "clippingMaskMode": 0,
  "do_objectID": "182E6239-4BBF-49A9-98E2-92464A74623E",
  "exportOptions": {
    "_class": "exportOptions",
    "exportFormats": [
    ],
    "includedLayerIds": [
    ],
    "layerOptions": 0,
    "shouldTrim": false
  },
  "frame": {
    "_class": "rect",
    "constrainProportions": false,
    "height": 6.666666666666666,
    "width": 28,
    "x": 0,
    "y": 13.33333333333337
  },
  "hasClickThrough": false,
  "hasClippingMask": false,
  "isFlippedHorizontal": false,
  "isFlippedVertical": false,
  "isLocked": false,
  "isVisible": true,
  "layerListExpandedType": 0,
  "layers": [
    {
      "class": "rectangle",
      "id": "AF480B80-7ABD-4C44-A439-0ACE69BC86B9"
    }
  ],
  "name": "Rectangle 2",
  "nameIsFixed": false,
  "resizingConstraint": 63,
  "resizingType": 0,
  "rotation": 0,
  "shouldBreakMaskChain": false,
  "style": {
    "_class": "style",
    "blur": {
      "_class": "blur",
      "center": "{0.5, 0.5}",
      "do_objectID": "1BF5374C-5B99-4F4C-80E0-665B138C6986",
      "isEnabled": false,
      "motionAngle": 0,
      "radius": 13.33333333333333,
      "type": 0
    },
    "borders": [
      {
        "_class": "border",
        "color": {
          "_class": "color",
          "alpha": 1,
          "blue": 0.592,
          "green": 0.592,
          "red": 0.592
        },
        "do_objectID": "4D6D26F9-00A6-4DDD-A7E0-2ED46BC01C94",
        "fillType": 0,
        "isEnabled": false,
        "position": 1,
        "thickness": 1.333333333333333
      }
    ],
    "endDecorationType": 0,
    "fills": [
      {
        "_class": "fill",
        "color": {
          "_class": "color",
          "alpha": 1,
          "blue": 0.2078431372549019,
          "green": 0.2313725490196077,
          "red": 0.8980392156862745
        },
        "do_objectID": "513C7CF1-C51D-40C1-9A75-A99934A74EF8",
        "fillType": 0,
        "gradient": {
          "_class": "gradient",
          "elipseLength": 1,
          "from": "{0.5, 0}",
          "gradientType": 0,
          "shouldSmoothenOpacity": true,
          "stops": [
            {
              "_class": "gradientStop",
              "color": {
                "_class": "color",
                "alpha": 1,
                "blue": 0.2084517265639092,
                "green": 0.2326253904725153,
                "red": 0.8974011479591837
              },
              "position": 0
            },
            {
              "_class": "gradientStop",
              "color": {
                "_class": "color",
                "alpha": 1,
                "blue": 0.1568627450980392,
                "green": 0.180392156862745,
                "red": 0.8274509803921568
              },
              "position": 1
            }
          ],
          "to": "{0.5, 1}"
        },
        "isEnabled": true,
        "noiseIndex": 0,
        "noiseIntensity": 0,
        "patternFillType": 0,
        "patternTileScale": 1
      }
    ],
    "innerShadows": [
      {
        "_class": "innerShadow",
        "blurRadius": 0,
        "color": {
          "_class": "color",
          "alpha": 1,
          "blue": 0.3932488952020202,
          "green": 0.8505105973686136,
          "red": 1
        },
        "contextSettings": {
          "_class": "graphicsContextSettings",
          "blendMode": 0,
          "opacity": 1
        },
        "do_objectID": "45CAB708-03D2-4CCB-89F3-9C8CFCB601F0",
        "isEnabled": false,
        "offsetX": 0,
        "offsetY": 1,
        "spread": 0
      }
    ],
    "miterLimit": 10,
    "shadows": [
      {
        "_class": "shadow",
        "blurRadius": 0,
        "color": {
          "_class": "color",
          "alpha": 0.06,
          "blue": 0,
          "green": 0,
          "red": 0
        },
        "contextSettings": {
          "_class": "graphicsContextSettings",
          "blendMode": 1,
          "opacity": 1
        },
        "do_objectID": "85E8DAD3-1BF3-45AB-B320-670609586E66",
        "isEnabled": false,
        "offsetX": 0,
        "offsetY": 0,
        "spread": 1
      }
    ],
    "startDecorationType": 0
  },
  "windingRule": 1
}