{
  "_class": "shapeGroup",
  "clippingMaskMode": 0,
  "do_objectID": "FC002D26-B192-4350-AE3F-C74CE5CAE4D4",
  "exportOptions": {
    "_class": "exportOptions",
    "exportFormats": [
    ],
    "includedLayerIds": [
    ],
    "layerOptions": 0,
    "shouldTrim": false
  },
  "frame": {
    "_class": "rect",
    "constrainProportions": false,
    "height": 9.080259183225294,
    "width": 10.09948437818588,
    "x": 13.3126367675095,
    "y": 5.586407483441349
  },
  "hasClickThrough": false,
  "hasClippingMask": false,
  "isFlippedHorizontal": false,
  "isFlippedVertical": false,
  "isLocked": false,
  "isVisible": true,
  "layerListExpandedType": 0,
  "layers": [
    {
      "class": "rectangle",
      "id": "FEC4011E-C25D-4E0C-A9DB-C6758F5C096E"
    }
  ],
  "name": "Rectangle 1067",
  "nameIsFixed": false,
  "resizingConstraint": 63,
  "resizingType": 0,
  "rotation": 0,
  "shouldBreakMaskChain": false,
  "style": {
    "_class": "style",
    "blur": {
      "_class": "blur",
      "center": "{0.5, 0.5}",
      "do_objectID": "7393E396-B8F8-44C8-BA7D-18EF650BB907",
      "isEnabled": false,
      "motionAngle": 0,
      "radius": 13.33333333333333,
      "type": 0
    },
    "borders": [
      {
        "_class": "border",
        "color": {
          "_class": "color",
          "alpha": 1,
          "blue": 0.592,
          "green": 0.592,
          "red": 0.592
        },
        "do_objectID": "A5A95FAC-99DE-4F31-8881-5557FB94AE8D",
        "fillType": 0,
        "isEnabled": false,
        "position": 1,
        "thickness": 1.333333333333333
      }
    ],
    "endDecorationType": 0,
    "fills": [
      {
        "_class": "fill",
        "color": {
          "_class": "color",
          "alpha": 1,
          "blue": 0.09411764705882353,
          "green": 0.7490196078431373,
          "red": 1
        },
        "do_objectID": "A9E3B402-0E05-425D-8A19-B214ECD6160D",
        "fillType": 0,
        "gradient": {
          "_class": "gradient",
          "elipseLength": 1,
          "from": "{0.5, 0}",
          "gradientType": 0,
          "shouldSmoothenOpacity": true,
          "stops": [
            {
              "_class": "gradientStop",
              "color": {
                "_class": "color",
                "alpha": 1,
                "blue": 0.09411764705882353,
                "green": 0.7490196078431373,
                "red": 1
              },
              "position": 0
            },
            {
              "_class": "gradientStop",
              "color": {
                "_class": "color",
                "alpha": 1,
                "blue": 0,
                "green": 0.7215686274509804,
                "red": 1
              },
              "position": 1
            }
          ],
          "to": "{0.5, 1}"
        },
        "isEnabled": true,
        "noiseIndex": 0,
        "noiseIntensity": 0,
        "patternFillType": 0,
        "patternTileScale": 1
      }
    ],
    "innerShadows": [
      {
        "_class": "innerShadow",
        "blurRadius": 0,
        "color": {
          "_class": "color",
          "alpha": 1,
          "blue": 0.3932488952020202,
          "green": 0.8505105973686136,
          "red": 1
        },
        "contextSettings": {
          "_class": "graphicsContextSettings",
          "blendMode": 0,
          "opacity": 1
        },
        "do_objectID": "801F9779-C576-49CD-B84F-75ED60DDC349",
        "isEnabled": false,
        "offsetX": 0,
        "offsetY": 1,
        "spread": 0
      }
    ],
    "miterLimit": 10,
    "shadows": [
      {
        "_class": "shadow",
        "blurRadius": 0,
        "color": {
          "_class": "color",
          "alpha": 0.06,
          "blue": 0,
          "green": 0,
          "red": 0
        },
        "contextSettings": {
          "_class": "graphicsContextSettings",
          "blendMode": 1,
          "opacity": 1
        },
        "do_objectID": "CDE8E5D0-BFC0-4AB8-932C-2E80062B241E",
        "isEnabled": false,
        "offsetX": 0,
        "offsetY": 1,
        "spread": 0
      }
    ],
    "startDecorationType": 0
  },
  "windingRule": 1
}