{
  "_class": "shapePath",
  "booleanOperation": -1,
  "do_objectID": "7385CA8C-0670-4D33-A8A8-B30A909C9ADC",
  "edited": true,
  "exportOptions": {
    "_class": "exportOptions",
    "exportFormats": [
    ],
    "includedLayerIds": [
    ],
    "layerOptions": 0,
    "shouldTrim": false
  },
  "frame": {
    "_class": "rect",
    "constrainProportions": false,
    "height": 13.33333333333333,
    "width": 13.33333333333333,
    "x": 0,
    "y": 0.5437571000055954
  },
  "isFlippedHorizontal": false,
  "isFlippedVertical": false,
  "isLocked": false,
  "isVisible": true,
  "layerListExpandedType": 0,
  "name": "Path",
  "nameIsFixed": false,
  "path": {
    "_class": "path",
    "isClosed": true,
    "pointRadiusBehaviour": 0,
    "points": [
      {
        "_class": "curvePoint",
        "cornerRadius": 0.6666666666666666,
        "curveFrom": "{0.55000000000000004, 0.29999999999999999}",
        "curveMode": 1,
        "curveTo": "{0.55000000000000004, 0.29999999999999999}",
        "do_objectID": "6BF614EE-A11B-4123-B28A-4FA4E3AD1636",
        "hasCurveFrom": false,
        "hasCurveTo": false,
        "point": "{0.5, 0.25}"
      },
      {
        "_class": "curvePoint",
        "cornerRadius": 0.6666666666666666,
        "curveFrom": "{0.55000000000000004, 0.20000000000000001}",
        "curveMode": 1,
        "curveTo": "{0.55000000000000004, 0.20000000000000001}",
        "do_objectID": "F4F69FC4-E053-4C36-B3FB-3E0F519E8AE5",
        "hasCurveFrom": false,
        "hasCurveTo": false,
        "point": "{0.55000000000000004, 0.20000000000000001}"
      },
      {
        "_class": "curvePoint",
        "cornerRadius": 0.6666666666666666,
        "curveFrom": "{0.65000000000000002, 0.10000000000000001}",
        "curveMode": 1,
        "curveTo": "{0.65000000000000002, 0.10000000000000001}",
        "do_objectID": "956A7051-7101-4C72-9115-EB7E6D62676C",
        "hasCurveFrom": false,
        "hasCurveTo": false,
        "point": "{0.65000000000000002, 0.10000000000000001}"
      },
      {
        "_class": "curvePoint",
        "cornerRadius": 0.6666666666666666,
        "curveFrom": "{0.75, 0.14999999999999999}",
        "curveMode": 1,
        "curveTo": "{0.75, 0.14999999999999999}",
        "do_objectID": "2C09E719-CABE-483F-8599-1A13DC94290E",
        "hasCurveFrom": false,
        "hasCurveTo": false,
        "point": "{0.75, 0.14999999999999999}"
      },
      {
        "_class": "curvePoint",
        "cornerRadius": 0.6666666666666666,
        "curveFrom": "{0.69623860677083327, 0.20188069661458335}",
        "curveMode": 1,
        "curveTo": "{0.69999999999999996, 0.20000000000000001}",
        "do_objectID": "9671D404-622A-467E-85CD-A9A95C322D0C",
        "hasCurveFrom": false,
        "hasCurveTo": false,
        "point": "{0.69999999999999996, 0.20000000000000001}"
      },
      {
        "_class": "curvePoint",
        "cornerRadius": 0.6666666666666666,
        "curveFrom": "{0.59999999999999998, 0.31450195312500001}",
        "curveMode": 1,
        "curveTo": "{0.62957194010416662, 0.28521402994791673}",
        "do_objectID": "62256E8A-578D-487D-A11A-CCD4E4455D7E",
        "hasCurveFrom": false,
        "hasCurveTo": false,
        "point": "{0.59999999999999998, 0.29999999999999999}"
      },
      {
        "_class": "curvePoint",
        "cornerRadius": 0.6666666666666666,
        "curveFrom": "{0.65000000000000002, 0.40000000000000002}",
        "curveMode": 1,
        "curveTo": "{0.65000000000000002, 0.38116861979166666}",
        "do_objectID": "460B32A7-1F94-4940-85D4-0502B270DCE3",
        "hasCurveFrom": false,
        "hasCurveTo": false,
        "point": "{0.65000000000000002, 0.40000000000000002}"
      },
      {
        "_class": "curvePoint",
        "cornerRadius": 0.6666666666666666,
        "curveFrom": "{0.67699869791666667, 0.43650065104166663}",
        "curveMode": 1,
        "curveTo": "{0.65000000000000002, 0.45000000000000001}",
        "do_objectID": "3C1EE631-6245-43AD-A2FA-19F490F41A4D",
        "hasCurveFrom": false,
        "hasCurveTo": false,
        "point": "{0.65000000000000002, 0.45000000000000001}"
      },
      {
        "_class": "curvePoint",
        "cornerRadius": 0.6666666666666666,
        "curveFrom": "{0.75, 0.40000000000000002}",
        "curveMode": 1,
        "curveTo": "{0.74366536458333343, 0.40316731770833336}",
        "do_objectID": "84974F2A-696F-41CF-9567-AC8D188E20AC",
        "hasCurveFrom": false,
        "hasCurveTo": false,
        "point": "{0.75, 0.40000000000000002}"
      },
      {
        "_class": "curvePoint",
        "cornerRadius": 0.6666666666666666,
        "curveFrom": "{0.69999999999999996, 0.34999999999999998}",
        "curveMode": 1,
        "curveTo": "{0.69999999999999996, 0.34999999999999998}",
        "do_objectID": "BAB945B7-C5C2-402C-BA4A-29A7E94F4E8D",
        "hasCurveFrom": false,
        "hasCurveTo": false,
        "point": "{0.69999999999999996, 0.34999999999999998}"
      },
      {
        "_class": "curvePoint",
        "cornerRadius": 0.6666666666666666,
        "curveFrom": "{0.75, 0.29999999999999999}",
        "curveMode": 1,
        "curveTo": "{0.75, 0.29999999999999999}",
        "do_objectID": "FF9A37F0-DDD4-435A-BF8B-1341013D3AEE",
        "hasCurveFrom": false,
        "hasCurveTo": false,
        "point": "{0.75, 0.29999999999999999}"
      },
      {
        "_class": "curvePoint",
        "cornerRadius": 0.6666666666666666,
        "curveFrom": "{0.80000000000000004, 0.20000000000000001}",
        "curveMode": 1,
        "curveTo": "{0.80000000000000004, 0.20000000000000001}",
        "do_objectID": "0F8D6DD7-CF1A-4C16-9801-FFAF9AF1F467",
        "hasCurveFrom": false,
        "hasCurveTo": false,
        "point": "{0.80000000000000004, 0.20000000000000001}"
      },
      {
        "_class": "curvePoint",
        "cornerRadius": 0.6666666666666666,
        "curveFrom": "{0.84999999999999998, 0}",
        "curveMode": 1,
        "curveTo": "{0.84999999999999998, 0}",
        "do_objectID": "568CD45E-31FB-45D5-9643-A15470BAE0AB",
        "hasCurveFrom": false,
        "hasCurveTo": false,
        "point": "{0.84999999999999998, 0}"
      },
      {
        "_class": "curvePoint",
        "cornerRadius": 0.6666666666666666,
        "curveFrom": "{1, 0.20000000000000001}",
        "curveMode": 1,
        "curveTo": "{1, 0.20000000000000001}",
        "do_objectID": "DE37D648-9B69-4813-B6F4-1244535C65D1",
        "hasCurveFrom": false,
        "hasCurveTo": false,
        "point": "{1, 0.20000000000000001}"
      },
      {
        "_class": "curvePoint",
        "cornerRadius": 0.6666666666666666,
        "curveFrom": "{1, 0.40000000000000002}",
        "curveMode": 1,
        "curveTo": "{1, 0.40000000000000002}",
        "do_objectID": "0B0C0E49-70E6-4E7B-A10E-AE1892BDB2BE",
        "hasCurveFrom": false,
        "hasCurveTo": false,
        "point": "{1, 0.40000000000000002}"
      },
      {
        "_class": "curvePoint",
        "cornerRadius": 0.6666666666666666,
        "curveFrom": "{0.94999999999999996, 0.5}",
        "curveMode": 1,
        "curveTo": "{0.94999999999999996, 0.5}",
        "do_objectID": "54CE8C6D-9F5B-421D-B309-AB9249CA89DD",
        "hasCurveFrom": false,
        "hasCurveTo": false,
        "point": "{0.94999999999999996, 0.5}"
      },
      {
        "_class": "curvePoint",
        "cornerRadius": 0.6666666666666666,
        "curveFrom": "{0.84999999999999998, 0.59999999999999998}",
        "curveMode": 1,
        "curveTo": "{0.84999999999999998, 0.59999999999999998}",
        "do_objectID": "E760F132-EDEB-4B42-B0DE-F420089B34BC",
        "hasCurveFrom": false,
        "hasCurveTo": false,
        "point": "{0.84999999999999998, 0.59999999999999998}"
      },
      {
        "_class": "curvePoint",
        "cornerRadius": 0.6666666666666666,
        "curveFrom": "{0.75, 0.65000000000000002}",
        "curveMode": 1,
        "curveTo": "{0.75, 0.65000000000000002}",
        "do_objectID": "0C367662-6A07-4274-B927-B1E631377A48",
        "hasCurveFrom": false,
        "hasCurveTo": false,
        "point": "{0.75, 0.65000000000000002}"
      },
      {
        "_class": "curvePoint",
        "cornerRadius": 0.6666666666666666,
        "curveFrom": "{0.65000000000000002, 0.65000000000000002}",
        "curveMode": 1,
        "curveTo": "{0.65000000000000002, 0.65000000000000002}",
        "do_objectID": "E9DC4763-BE71-48E0-BDE2-8653043EE888",
        "hasCurveFrom": false,
        "hasCurveTo": false,
        "point": "{0.65000000000000002, 0.65000000000000002}"
      },
      {
        "_class": "curvePoint",
        "cornerRadius": 0.6666666666666666,
        "curveFrom": "{0.75, 0.69999999999999996}",
        "curveMode": 1,
        "curveTo": "{0.75, 0.69999999999999996}",
        "do_objectID": "807F019C-66D7-4889-B754-5DC911A03CD9",
        "hasCurveFrom": false,
        "hasCurveTo": false,
        "point": "{0.75, 0.69999999999999996}"
      },
      {
        "_class": "curvePoint",
        "cornerRadius": 0.6666666666666666,
        "curveFrom": "{0.80000000000000004, 0.75}",
        "curveMode": 1,
        "curveTo": "{0.80000000000000004, 0.75}",
        "do_objectID": "D22481FA-1074-41CA-BC3F-2781B6C7A094",
        "hasCurveFrom": false,
        "hasCurveTo": false,
        "point": "{0.80000000000000004, 0.75}"
      },
      {
        "_class": "curvePoint",
        "cornerRadius": 0.6666666666666666,
        "curveFrom": "{0.84999999999999998, 0.69999999999999996}",
        "curveMode": 1,
        "curveTo": "{0.84999999999999998, 0.69999999999999996}",
        "do_objectID": "CAB4C5BE-A5FE-422B-BE42-F2C4A71A5D65",
        "hasCurveFrom": false,
        "hasCurveTo": false,
        "point": "{0.84999999999999998, 0.69999999999999996}"
      },
      {
        "_class": "curvePoint",
        "cornerRadius": 0.6666666666666666,
        "curveFrom": "{0.90000000000000002, 0.75}",
        "curveMode": 1,
        "curveTo": "{0.90000000000000002, 0.75}",
        "do_objectID": "053200A3-8770-433D-9CFD-AC7E544A04AC",
        "hasCurveFrom": false,
        "hasCurveTo": false,
        "point": "{0.90000000000000002, 0.75}"
      },
      {
        "_class": "curvePoint",
        "cornerRadius": 0.6666666666666666,
        "curveFrom": "{0.84999999999999998, 0.84999999999999998}",
        "curveMode": 1,
        "curveTo": "{0.84999999999999998, 0.84999999999999998}",
        "do_objectID": "F777DEE5-1B7D-453E-881C-CDD1AC4C90F2",
        "hasCurveFrom": false,
        "hasCurveTo": false,
        "point": "{0.84999999999999998, 0.84999999999999998}"
      },
      {
        "_class": "curvePoint",
        "cornerRadius": 0.6666666666666666,
        "curveFrom": "{0.75, 0.84999999999999998}",
        "curveMode": 1,
        "curveTo": "{0.75, 0.84999999999999998}",
        "do_objectID": "E2041B3C-3861-4552-AA11-5C0F1568FA17",
        "hasCurveFrom": false,
        "hasCurveTo": false,
        "point": "{0.75, 0.84999999999999998}"
      },
      {
        "_class": "curvePoint",
        "cornerRadius": 0.6666666666666666,
        "curveFrom": "{0.65000000000000002, 0.80000000000000004}",
        "curveMode": 1,
        "curveTo": "{0.65000000000000002, 0.80000000000000004}",
        "do_objectID": "382B8859-F123-4880-85D1-D7C7682A26B8",
        "hasCurveFrom": false,
        "hasCurveTo": false,
        "point": "{0.65000000000000002, 0.80000000000000004}"
      },
      {
        "_class": "curvePoint",
        "cornerRadius": 0.6666666666666666,
        "curveFrom": "{0.59999999999999998, 0.69999999999999996}",
        "curveMode": 1,
        "curveTo": "{0.59999999999999998, 0.69999999999999996}",
        "do_objectID": "CA0240B1-29F2-42DE-897E-F9FF85471A71",
        "hasCurveFrom": false,
        "hasCurveTo": false,
        "point": "{0.59999999999999998, 0.69999999999999996}"
      },
      {
        "_class": "curvePoint",
        "cornerRadius": 0.6666666666666666,
        "curveFrom": "{0.55000000000000004, 0.75}",
        "curveMode": 1,
        "curveTo": "{0.55000000000000004, 0.75}",
        "do_objectID": "A54B3617-DC3F-48CB-9793-56D33307DFEA",
        "hasCurveFrom": false,
        "hasCurveTo": false,
        "point": "{0.55000000000000004, 0.75}"
      },
      {
        "_class": "curvePoint",
        "cornerRadius": 0.6666666666666666,
        "curveFrom": "{0.65000000000000002, 0.90000000000000002}",
        "curveMode": 1,
        "curveTo": "{0.65000000000000002, 0.90000000000000002}",
        "do_objectID": "C806521D-DE63-4918-A680-726430351402",
        "hasCurveFrom": false,
        "hasCurveTo": false,
        "point": "{0.65000000000000002, 0.90000000000000002}"
      },
      {
        "_class": "curvePoint",
        "cornerRadius": 0.6666666666666666,
        "curveFrom": "{0.5, 1}",
        "curveMode": 1,
        "curveTo": "{0.5, 1}",
        "do_objectID": "B4430386-3195-4663-9BE8-A237307B5863",
        "hasCurveFrom": false,
        "hasCurveTo": false,
        "point": "{0.5, 1}"
      },
      {
        "_class": "curvePoint",
        "cornerRadius": 0.6666666666666666,
        "curveFrom": "{0.34999999999999998, 0.90000000000000002}",
        "curveMode": 1,
        "curveTo": "{0.34999999999999998, 0.90000000000000002}",
        "do_objectID": "204C756D-7E52-45B9-9EC5-31069A1C891E",
        "hasCurveFrom": false,
        "hasCurveTo": false,
        "point": "{0.34999999999999998, 0.90000000000000002}"
      },
      {
        "_class": "curvePoint",
        "cornerRadius": 0.6666666666666666,
        "curveFrom": "{0.45000000000000001, 0.75}",
        "curveMode": 1,
        "curveTo": "{0.45000000000000001, 0.75}",
        "do_objectID": "2251B2A9-50F2-44F6-96F3-5F4672B30D88",
        "hasCurveFrom": false,
        "hasCurveTo": false,
        "point": "{0.45000000000000001, 0.75}"
      },
      {
        "_class": "curvePoint",
        "cornerRadius": 0.6666666666666666,
        "curveFrom": "{0.40000000000000002, 0.69999999999999996}",
        "curveMode": 1,
        "curveTo": "{0.40000000000000002, 0.69999999999999996}",
        "do_objectID": "5069D2A7-65E4-45BF-A6FF-3C7C98ED63C8",
        "hasCurveFrom": false,
        "hasCurveTo": false,
        "point": "{0.40000000000000002, 0.69999999999999996}"
      },
      {
        "_class": "curvePoint",
        "cornerRadius": 0.6666666666666666,
        "curveFrom": "{0.34999999999999998, 0.80000000000000004}",
        "curveMode": 1,
        "curveTo": "{0.34999999999999998, 0.80000000000000004}",
        "do_objectID": "43C15760-7D63-40D5-B761-8002AB20E0F7",
        "hasCurveFrom": false,
        "hasCurveTo": false,
        "point": "{0.34999999999999998, 0.80000000000000004}"
      },
      {
        "_class": "curvePoint",
        "cornerRadius": 0.6666666666666666,
        "curveFrom": "{0.25, 0.84999999999999998}",
        "curveMode": 1,
        "curveTo": "{0.25, 0.84999999999999998}",
        "do_objectID": "8C072A66-817B-4E24-819A-A4E8D89B7C8C",
        "hasCurveFrom": false,
        "hasCurveTo": false,
        "point": "{0.25, 0.84999999999999998}"
      },
      {
        "_class": "curvePoint",
        "cornerRadius": 0.6666666666666666,
        "curveFrom": "{0.14999999999999999, 0.84999999999999998}",
        "curveMode": 1,
        "curveTo": "{0.14999999999999999, 0.84999999999999998}",
        "do_objectID": "509F8829-7ABC-42DF-8E4A-9AA4EA719637",
        "hasCurveFrom": false,
        "hasCurveTo": false,
        "point": "{0.14999999999999999, 0.84999999999999998}"
      },
      {
        "_class": "curvePoint",
        "cornerRadius": 0.6666666666666666,
        "curveFrom": "{0.10000000000000001, 0.75}",
        "curveMode": 1,
        "curveTo": "{0.10000000000000001, 0.75}",
        "do_objectID": "1D788A2B-01BF-4F74-B370-51C313A54CD1",
        "hasCurveFrom": false,
        "hasCurveTo": false,
        "point": "{0.10000000000000001, 0.75}"
      },
      {
        "_class": "curvePoint",
        "cornerRadius": 0.6666666666666666,
        "curveFrom": "{0.14999999999999999, 0.69999999999999996}",
        "curveMode": 1,
        "curveTo": "{0.14999999999999999, 0.69999999999999996}",
        "do_objectID": "2F07D0BF-202B-410E-BFD0-36DD461B73C4",
        "hasCurveFrom": false,
        "hasCurveTo": false,
        "point": "{0.14999999999999999, 0.69999999999999996}"
      },
      {
        "_class": "curvePoint",
        "cornerRadius": 0.6666666666666666,
        "curveFrom": "{0.20000000000000001, 0.75}",
        "curveMode": 1,
        "curveTo": "{0.20000000000000001, 0.75}",
        "do_objectID": "E47D13D0-31C1-4D4E-ACF7-3C99DE66990D",
        "hasCurveFrom": false,
        "hasCurveTo": false,
        "point": "{0.20000000000000001, 0.75}"
      },
      {
        "_class": "curvePoint",
        "cornerRadius": 0.6666666666666666,
        "curveFrom": "{0.25, 0.69999999999999996}",
        "curveMode": 1,
        "curveTo": "{0.25, 0.69999999999999996}",
        "do_objectID": "5816960D-27E1-40AD-9986-8706081B061C",
        "hasCurveFrom": false,
        "hasCurveTo": false,
        "point": "{0.25, 0.69999999999999996}"
      },
      {
        "_class": "curvePoint",
        "cornerRadius": 0.6666666666666666,
        "curveFrom": "{0.34999999999999998, 0.65000000000000002}",
        "curveMode": 1,
        "curveTo": "{0.34999999999999998, 0.65000000000000002}",
        "do_objectID": "F585AFC2-BE54-4A98-9E94-8D1E9DFB3094",
        "hasCurveFrom": false,
        "hasCurveTo": false,
        "point": "{0.34999999999999998, 0.65000000000000002}"
      },
      {
        "_class": "curvePoint",
        "cornerRadius": 0.6666666666666666,
        "curveFrom": "{0.25, 0.65000000000000002}",
        "curveMode": 1,
        "curveTo": "{0.25, 0.65000000000000002}",
        "do_objectID": "B27835F7-8B13-4579-8E67-3685FE3ED316",
        "hasCurveFrom": false,
        "hasCurveTo": false,
        "point": "{0.25, 0.65000000000000002}"
      },
      {
        "_class": "curvePoint",
        "cornerRadius": 0.6666666666666666,
        "curveFrom": "{0.14999999999999999, 0.59999999999999998}",
        "curveMode": 1,
        "curveTo": "{0.14999999999999999, 0.59999999999999998}",
        "do_objectID": "6A174634-E858-4015-B977-260EB348B138",
        "hasCurveFrom": false,
        "hasCurveTo": false,
        "point": "{0.14999999999999999, 0.59999999999999998}"
      },
      {
        "_class": "curvePoint",
        "cornerRadius": 0.6666666666666666,
        "curveFrom": "{0.050000000000000003, 0.5}",
        "curveMode": 1,
        "curveTo": "{0.050000000000000003, 0.5}",
        "do_objectID": "E271ACEC-978F-4335-8381-23CB69DEF074",
        "hasCurveFrom": false,
        "hasCurveTo": false,
        "point": "{0.050000000000000003, 0.5}"
      },
      {
        "_class": "curvePoint",
        "cornerRadius": 0.6666666666666666,
        "curveFrom": "{0, 0.40000000000000002}",
        "curveMode": 1,
        "curveTo": "{0, 0.40000000000000002}",
        "do_objectID": "1BC1639A-0FB6-41BD-8D86-DC9AF026C750",
        "hasCurveFrom": false,
        "hasCurveTo": false,
        "point": "{0, 0.40000000000000002}"
      },
      {
        "_class": "curvePoint",
        "cornerRadius": 0.6666666666666666,
        "curveFrom": "{0, 0.20000000000000001}",
        "curveMode": 1,
        "curveTo": "{0, 0.20000000000000001}",
        "do_objectID": "D51AE326-0C79-4095-A048-6F427CF76A74",
        "hasCurveFrom": false,
        "hasCurveTo": false,
        "point": "{0, 0.20000000000000001}"
      },
      {
        "_class": "curvePoint",
        "cornerRadius": 0.6666666666666666,
        "curveFrom": "{0.14999999999999999, 0}",
        "curveMode": 1,
        "curveTo": "{0.14999999999999999, 0}",
        "do_objectID": "94B01B73-5561-4745-A865-1F6DD7BDCBD7",
        "hasCurveFrom": false,
        "hasCurveTo": false,
        "point": "{0.14999999999999999, 0}"
      },
      {
        "_class": "curvePoint",
        "cornerRadius": 0.6666666666666666,
        "curveFrom": "{0.20000000000000001, 0.20000000000000001}",
        "curveMode": 1,
        "curveTo": "{0.20000000000000001, 0.20000000000000001}",
        "do_objectID": "7D9B2B3A-DCBF-41D6-9BB2-DF11738F25EB",
        "hasCurveFrom": false,
        "hasCurveTo": false,
        "point": "{0.20000000000000001, 0.20000000000000001}"
      },
      {
        "_class": "curvePoint",
        "cornerRadius": 0.6666666666666666,
        "curveFrom": "{0.25, 0.29999999999999999}",
        "curveMode": 1,
        "curveTo": "{0.25, 0.29999999999999999}",
        "do_objectID": "29DA42F5-F50F-4ED0-8FFA-131E16B1EB73",
        "hasCurveFrom": false,
        "hasCurveTo": false,
        "point": "{0.25, 0.29999999999999999}"
      },
      {
        "_class": "curvePoint",
        "cornerRadius": 0.6666666666666666,
        "curveFrom": "{0.29999999999999999, 0.34999999999999998}",
        "curveMode": 1,
        "curveTo": "{0.29999999999999999, 0.34999999999999998}",
        "do_objectID": "9666D95A-68B7-4B70-8B5D-919835F50749",
        "hasCurveFrom": false,
        "hasCurveTo": false,
        "point": "{0.29999999999999999, 0.34999999999999998}"
      },
      {
        "_class": "curvePoint",
        "cornerRadius": 0.6666666666666666,
        "curveFrom": "{0.25, 0.40000000000000002}",
        "curveMode": 1,
        "curveTo": "{0.25, 0.40000000000000002}",
        "do_objectID": "C7EB23E1-2152-4206-9635-0622E03CD299",
        "hasCurveFrom": false,
        "hasCurveTo": false,
        "point": "{0.25, 0.40000000000000002}"
      },
      {
        "_class": "curvePoint",
        "cornerRadius": 0.6666666666666666,
        "curveFrom": "{0.34999999999999998, 0.45000000000000001}",
        "curveMode": 1,
        "curveTo": "{0.34999999999999998, 0.45000000000000001}",
        "do_objectID": "D7A26C07-8C0A-4C63-93C2-BF2E19B9EA6E",
        "hasCurveFrom": false,
        "hasCurveTo": false,
        "point": "{0.34999999999999998, 0.45000000000000001}"
      },
      {
        "_class": "curvePoint",
        "cornerRadius": 0.6666666666666666,
        "curveFrom": "{0.34999999999999998, 0.40000000000000002}",
        "curveMode": 1,
        "curveTo": "{0.34999999999999998, 0.40000000000000002}",
        "do_objectID": "5CA70FCC-15EC-4AB5-ADBE-E87263FBEDBD",
        "hasCurveFrom": false,
        "hasCurveTo": false,
        "point": "{0.34999999999999998, 0.40000000000000002}"
      },
      {
        "_class": "curvePoint",
        "cornerRadius": 0.6666666666666666,
        "curveFrom": "{0.40000000000000002, 0.29999999999999999}",
        "curveMode": 1,
        "curveTo": "{0.40000000000000002, 0.29999999999999999}",
        "do_objectID": "77F377D1-624B-4BA0-82E1-EC550BC6FF2A",
        "hasCurveFrom": false,
        "hasCurveTo": false,
        "point": "{0.40000000000000002, 0.29999999999999999}"
      },
      {
        "_class": "curvePoint",
        "cornerRadius": 0.6666666666666666,
        "curveFrom": "{0.29999999999999999, 0.20000000000000001}",
        "curveMode": 1,
        "curveTo": "{0.29999999999999999, 0.20000000000000001}",
        "do_objectID": "2D446688-A818-48E0-A119-EC3B2B59AECB",
        "hasCurveFrom": false,
        "hasCurveTo": false,
        "point": "{0.29999999999999999, 0.20000000000000001}"
      },
      {
        "_class": "curvePoint",
        "cornerRadius": 0.6666666666666666,
        "curveFrom": "{0.25, 0.14999999999999999}",
        "curveMode": 1,
        "curveTo": "{0.25, 0.14999999999999999}",
        "do_objectID": "12C1B065-D4DF-459F-B49C-19BDCCA1D663",
        "hasCurveFrom": false,
        "hasCurveTo": false,
        "point": "{0.25, 0.14999999999999999}"
      },
      {
        "_class": "curvePoint",
        "cornerRadius": 0.6666666666666666,
        "curveFrom": "{0.34999999999999998, 0.10000000000000001}",
        "curveMode": 1,
        "curveTo": "{0.34999999999999998, 0.10000000000000001}",
        "do_objectID": "32424944-1C3F-4912-892A-DE904C29D1AA",
        "hasCurveFrom": false,
        "hasCurveTo": false,
        "point": "{0.34999999999999998, 0.10000000000000001}"
      },
      {
        "_class": "curvePoint",
        "cornerRadius": 0.6666666666666666,
        "curveFrom": "{0.45000000000000001, 0.20000000000000001}",
        "curveMode": 1,
        "curveTo": "{0.45000000000000001, 0.20000000000000001}",
        "do_objectID": "79486ED8-9FAA-4C10-8255-F7E39A575E38",
        "hasCurveFrom": false,
        "hasCurveTo": false,
        "point": "{0.45000000000000001, 0.20000000000000001}"
      }
    ]
  },
  "resizingConstraint": 63,
  "resizingType": 0,
  "rotation": 0,
  "shouldBreakMaskChain": false
}